markopolis/__init__.py
markopolis/upload.py
markopolis-3.0.1.dist-info/METADATA
markopolis-3.0.1.dist-info/WHEEL
markopolis-3.0.1.dist-info/entry_points.txt
markopolis-3.0.1.dist-info/RECORD
